timems/__init__.py
timems-1.0.1.dist-info/LICENSE.txt
timems-1.0.1.dist-info/METADATA
timems-1.0.1.dist-info/WHEEL
timems-1.0.1.dist-info/top_level.txt
timems-1.0.1.dist-info/RECORD
