Metadata-Version: 2.1
Name: timems
Version: 1.0.1
Summary: Variable time formats in one package
Author: Jamsson
Author-email: ingaburke966@gmail.com
License: UNKNOWN
Keywords: python,time,tools,utils,formats,seconds
Platform: UNKNOWN
License-File: LICENSE.txt
